vihhlima_image_processing/__init__.py
vihhlima_image_processing/utils/__init__.py
vihhlima_image_processing/utils/io.py
vihhlima_image_processsing-0.0.1.dist-info/METADATA
vihhlima_image_processsing-0.0.1.dist-info/WHEEL
vihhlima_image_processsing-0.0.1.dist-info/top_level.txt
vihhlima_image_processsing-0.0.1.dist-info/RECORD
