Metadata-Version: 2.1
Name: vihhlima-image-processsing
Version: 0.0.1
Summary: Image processing package
Home-page: https://github.com/vihhlimabr/Image-Processing-Package.git
Author: Vitor Lima
Author-email: vihhlima@hotmail.com
Requires-Python: >=3.8
